pypowerup/__init__.py
pypowerup/core.py
pypowerup-0.1.0.dist-info/LICENSE
pypowerup-0.1.0.dist-info/METADATA
pypowerup-0.1.0.dist-info/WHEEL
pypowerup-0.1.0.dist-info/top_level.txt
pypowerup-0.1.0.dist-info/RECORD
