Metadata-Version: 2.1
Name: pypowerup
Version: 0.1.0
Summary: Power analysis tool for experimental and quasi-experimental designs
Home-page: https://github.com/sophiamyang/pypowerup
Author: Sophia Man Yang
License: BSD license
Keywords: pypowerup
Platform: UNKNOWN
Classifier: Development Status :: 2 - Pre-Alpha
Classifier: Intended Audience :: Developers
Classifier: License :: OSI Approved :: BSD License
Classifier: Natural Language :: English
Classifier: Programming Language :: Python :: 3
Classifier: Programming Language :: Python :: 3.6
Classifier: Programming Language :: Python :: 3.7
Classifier: Programming Language :: Python :: 3.8
Requires-Dist: scipy
Requires-Dist: numpy
Requires-Dist: innerscope
